tp_html/__init__.py
tp_html-0.1.2.dist-info/LICENSE
tp_html-0.1.2.dist-info/METADATA
tp_html-0.1.2.dist-info/WHEEL
tp_html-0.1.2.dist-info/top_level.txt
tp_html-0.1.2.dist-info/RECORD
