Metadata-Version: 2.1
Name: tp-html
Version: 0.1.2
Summary: Get data from html
Home-page: https://github.com/jhyao/tp_html
Author: jhyao
Author-email: yaojinhonggg@gmail.com
License: UNKNOWN
Platform: UNKNOWN
Classifier: Programming Language :: Python :: 3
Classifier: License :: OSI Approved :: MIT License
Classifier: Operating System :: OS Independent
Requires-Dist: beautifulsoup4
